apres/__init__.py
apres/__main__.py
apres/apres_to_nc.py
apres/nc_to_apres.py
apres/plot_apres.py
apres/read_apres.py
apres/write_apres.py
bas_apres-0.4.2.dist-info/entry_points.txt
bas_apres-0.4.2.dist-info/LICENSE
bas_apres-0.4.2.dist-info/WHEEL
bas_apres-0.4.2.dist-info/METADATA
bas_apres-0.4.2.dist-info/RECORD
