Metadata-Version: 2.1
Name: bas-apres
Version: 0.4.2
Summary: Package for working with BAS ApRES files
Home-page: https://github.com/antarctica/bas-apres
License: Apache-2.0
Author: Paul Breen
Author-email: pbree@bas.ac.uk
Requires-Python: >=3.8,<4.0
Classifier: License :: OSI Approved :: Apache Software License
Classifier: Programming Language :: Python :: 3
Classifier: Programming Language :: Python :: 3.8
Classifier: Programming Language :: Python :: 3.9
Classifier: Programming Language :: Python :: 3.10
Classifier: Programming Language :: Python :: 3.11
Provides-Extra: remote
Requires-Dist: fsspec (>=2024.10.0,<2025.0.0); extra == "remote"
Requires-Dist: matplotlib (>=3.4.3,<4.0.0)
Requires-Dist: netCDF4 (>=1.5.2,<2.0.0)
Requires-Dist: numpy (>=1.17.2,<2.0.0)
Project-URL: Documentation, https://antarctica.github.io/bas-apres/
Project-URL: Repository, https://github.com/antarctica/bas-apres
